login/__init__.py
login/admin.py
login/apps.py
login/models.py
login/tests.py
login/tokens.py
login/urls.py
login/views.py
login/migrations/__init__.py
login/static/bootstrap-4.5.2/dist/css/bootstrap-grid.css
login/static/bootstrap-4.5.2/dist/css/bootstrap-grid.css.map
login/static/bootstrap-4.5.2/dist/css/bootstrap-grid.min.css
login/static/bootstrap-4.5.2/dist/css/bootstrap-grid.min.css.map
login/static/bootstrap-4.5.2/dist/css/bootstrap-reboot.css
login/static/bootstrap-4.5.2/dist/css/bootstrap-reboot.css.map
login/static/bootstrap-4.5.2/dist/css/bootstrap-reboot.min.css
login/static/bootstrap-4.5.2/dist/css/bootstrap-reboot.min.css.map
login/static/bootstrap-4.5.2/dist/css/bootstrap.css
login/static/bootstrap-4.5.2/dist/css/bootstrap.css.map
login/static/bootstrap-4.5.2/dist/css/bootstrap.min.css
login/static/bootstrap-4.5.2/dist/css/bootstrap.min.css.map
login/static/bootstrap-4.5.2/dist/js/bootstrap.bundle.js
login/static/bootstrap-4.5.2/dist/js/bootstrap.bundle.js.map
login/static/bootstrap-4.5.2/dist/js/bootstrap.bundle.min.js
login/static/bootstrap-4.5.2/dist/js/bootstrap.bundle.min.js.map
login/static/bootstrap-4.5.2/dist/js/bootstrap.js
login/static/bootstrap-4.5.2/dist/js/bootstrap.js.map
login/static/bootstrap-4.5.2/dist/js/bootstrap.min.js
login/static/bootstrap-4.5.2/dist/js/bootstrap.min.js.map
login/templates/login/email_template.html
login/templates/login/login.html
login/templates/login/notice_template.html
login/templates/login/register.html
django_user_login_register_activate-2.4.dist-info/LICENSE
django_user_login_register_activate-2.4.dist-info/METADATA
django_user_login_register_activate-2.4.dist-info/WHEEL
django_user_login_register_activate-2.4.dist-info/top_level.txt
django_user_login_register_activate-2.4.dist-info/RECORD
