Metadata-Version: 2.1
Name: django-user-login-register-activate
Version: 2.4
Summary: A Django app to signup, activation, login and logout.
Home-page: https://github.com/xiaoxuanzi/django-user-login-register-activate
Author: xiaoxuanzi
Author-email: xiaoximou@gmail.com
License: MIT License
Keywords: django,accounts,login
Platform: UNKNOWN
Classifier: Environment :: Web Environment
Classifier: Framework :: Django
Classifier: Framework :: Django :: 2.1
Classifier: Intended Audience :: Developers
Classifier: License :: OSI Approved :: MIT License
Classifier: Operating System :: OS Independent
Classifier: Programming Language :: Python
Classifier: Programming Language :: Python :: 3
Classifier: Programming Language :: Python :: 3.5
Classifier: Programming Language :: Python :: 3.6
Classifier: Programming Language :: Python :: 3.7
Classifier: Programming Language :: Python :: 3.8
Classifier: Topic :: Internet :: WWW/HTTP
Classifier: Topic :: Internet :: WWW/HTTP :: Dynamic Content
